.DS_Store
bradocs4py/__init__.py
bradocs4py/chaveacessonfe.py
bradocs4py/cnpj.py
bradocs4py/cpf.py
bradocs4py/documentoidentificacao.py
bradocs4py/gtin.py
bradocs4py/inscricaoestadual.py
bradocs4py/inscricaosuframa.py
bradocs4py/validadoresie/__init__.py
bradocs4py/validadoresie/validadorac.py
bradocs4py/validadoresie/validadoral.py
bradocs4py/validadoresie/validadoram.py
bradocs4py/validadoresie/validadorap.py
bradocs4py/validadoresie/validadorba.py
bradocs4py/validadoresie/validadorce.py
bradocs4py/validadoresie/validadordf.py
bradocs4py/validadoresie/validadores.py
bradocs4py/validadoresie/validadorgo.py
bradocs4py/validadoresie/validadorma.py
bradocs4py/validadoresie/validadormg.py
bradocs4py/validadoresie/validadorms.py
bradocs4py/validadoresie/validadormt.py
bradocs4py/validadoresie/validadorpa.py
bradocs4py/validadoresie/validadorpb.py
bradocs4py/validadoresie/validadorpe.py
bradocs4py/validadoresie/validadorpi.py
bradocs4py/validadoresie/validadorpr.py
bradocs4py/validadoresie/validadorrj.py
bradocs4py/validadoresie/validadorrn.py
bradocs4py/validadoresie/validadorro.py
bradocs4py/validadoresie/validadorrr.py
bradocs4py/validadoresie/validadorrs.py
bradocs4py/validadoresie/validadorsc.py
bradocs4py/validadoresie/validadorse.py
bradocs4py/validadoresie/validadorsp.py
bradocs4py/validadoresie/validadorto.py
bradocs4py-1.3.1.0.dist-info/LICENSE
bradocs4py-1.3.1.0.dist-info/METADATA
bradocs4py-1.3.1.0.dist-info/WHEEL
bradocs4py-1.3.1.0.dist-info/top_level.txt
bradocs4py-1.3.1.0.dist-info/zip-safe
bradocs4py-1.3.1.0.dist-info/RECORD
