Metadata-Version: 2.1
Name: bradocs4py
Version: 1.3.1.0
Summary: Implementa a funcionalidade validar_inscao_estadual.
Home-page: https://github.com/namio/BRADocs4Py.git
Author: Nâmio Evangelista Cavalcante de Sousa
Author-email: namio.sousa@gmail.com
License: MIT
Keywords: cpf cnpj documentos brasileiros receita federal
Platform: UNKNOWN
Classifier: Development Status :: 3 - Alpha
Classifier: Environment :: Web Environment
Classifier: Intended Audience :: Developers
Classifier: License :: OSI Approved :: MIT License
Classifier: Natural Language :: English
Classifier: Natural Language :: Portuguese
Classifier: Natural Language :: Portuguese (Brazilian)
Classifier: Programming Language :: Python :: 3.6
Classifier: Programming Language :: Python :: 3.7
Requires-Python: >=3
